content_genome_mapper/__init__.py
content_genome_mapper/__main__.py
content_genome_mapper/cli.py
content_genome_mapper/core/__init__.py
content_genome_mapper/core/comparer.py
content_genome_mapper/core/crawler.py
content_genome_mapper/core/extractor.py
content_genome_mapper/core/salience.py
content_genome_mapper/core/visualizer.py
content_genome_mapper-0.1.0.dist-info/licenses/LICENSE
tests/__init__.py
content_genome_mapper-0.1.0.dist-info/METADATA
content_genome_mapper-0.1.0.dist-info/WHEEL
content_genome_mapper-0.1.0.dist-info/entry_points.txt
content_genome_mapper-0.1.0.dist-info/top_level.txt
content_genome_mapper-0.1.0.dist-info/RECORD
