Metadata-Version: 2.4
Name: content-genome-mapper
Version: 0.1.0
Summary: 🧬 A CLI tool to crawl, analyze, and extract content structure semantically.
Author: Your Name
Author-email: Amal Alexander <amalalex95@email.com>
License: MIT
Project-URL: Homepage, https://github.com/amal-alexander
Project-URL: Repository, https://github.com/amal-alexander?tab=repositories
Requires-Python: >=3.8
License-File: LICENSE
Requires-Dist: typer[all]
Requires-Dist: requests
Requires-Dist: beautifulsoup4
Requires-Dist: spacy
Requires-Dist: scikit-learn
Requires-Dist: pandas
Requires-Dist: jinja2
Requires-Dist: sentence-transformers
Requires-Dist: textblob
Requires-Dist: rich
Dynamic: author
Dynamic: license-file
Dynamic: requires-python
